{"DN7FbIXULoHQnPxZQEVjzQo9pbe":"C:\\dentalempireos\\tmp\\import-10-personal-brand\\images\\img_01.webp","BORpbRwQpo4xaTxI1rxj4qzIpqc":"C:\\dentalempireos\\tmp\\import-10-personal-brand\\images\\img_02.webp","MV3xbyvRVoVJ7MxcXyvj0UMJpng":"C:\\dentalempireos\\tmp\\import-10-personal-brand\\images\\img_03.webp","O6mGbGERcoB1DPxBvb4jcOnspKc":"C:\\dentalempireos\\tmp\\import-10-personal-brand\\images\\img_04.webp","JrW7bHpc4oXADAxf40AjzHVCpPg":"C:\\dentalempireos\\tmp\\import-10-personal-brand\\images\\img_05.webp","A72Xbc8o9oaZK6xoHqEjyLpgpFf":"C:\\dentalempireos\\tmp\\import-10-personal-brand\\images\\img_06.webp","LZElb99W2os69jxgiJHjcaJEpUb":"C:\\dentalempireos\\tmp\\import-10-personal-brand\\images\\img_07.webp","PqIjbkbjsoXF6kxd8HWjuhJXpNc":"C:\\dentalempireos\\tmp\\import-10-personal-brand\\images\\img_08.webp","Ydd8bSfI9oqZ7LxIbM3juD4qp2c":"C:\\dentalempireos\\tmp\\import-10-personal-brand\\images\\img_09.webp","OnUNbZFu3ommQex9bjRjhARcpde":"C:\\dentalempireos\\tmp\\import-10-personal-brand\\images\\img_10.webp","QcEWbwNC8oiVdLxMVrVjL6Lap5n":"C:\\dentalempireos\\tmp\\import-10-personal-brand\\images\\img_11.webp","EhWHbuz2EohwVKx1kGzjBne5pMf":"C:\\dentalempireos\\tmp\\import-10-personal-brand\\images\\img_12.webp","JkDfboLCDopTrsxfmsvjHpXhpOg":"C:\\dentalempireos\\tmp\\import-10-personal-brand\\images\\img_13.webp","LyW7btMraoYXNExUvTejPAQ2ptg":"C:\\dentalempireos\\tmp\\import-10-personal-brand\\images\\img_14.webp","WJhwb5dGWoASOAx0rWOjVy8Eprc":"C:\\dentalempireos\\tmp\\import-10-personal-brand\\images\\img_15.webp","EFUJblvgdoCJBex0lQajUbFYp8c":"C:\\dentalempireos\\tmp\\import-10-personal-brand\\images\\img_16.webp","XUfCbwXlvoZYIyxfF6UjuGCbpQg":"C:\\dentalempireos\\tmp\\import-10-personal-brand\\images\\img_17.webp"}