{"OOOdbVqrgoIYS6xIX9WjkKWJp1c":"c:\\dentalempireos\\tmp\\import-14-trust-assets\\images\\img_01.webp","U2kqbB4lSoq3R2xBZP4jgXHnpPe":"c:\\dentalempireos\\tmp\\import-14-trust-assets\\images\\img_02.webp","QyjWbfzGmozspVx2DKqjpKPMpDd":"c:\\dentalempireos\\tmp\\import-14-trust-assets\\images\\img_03.webp","FrBVbqpjmoHbJ0xXoEPjV3OSpYd":"c:\\dentalempireos\\tmp\\import-14-trust-assets\\images\\img_04.webp","SGwfbkjS8opSEaxy8LNjjfzBpgh":"c:\\dentalempireos\\tmp\\import-14-trust-assets\\images\\img_05.webp","QR38b729cojFfIx5wyqjU4bYpVr":"c:\\dentalempireos\\tmp\\import-14-trust-assets\\images\\img_06.webp","G2pDbny7YozRnixSsTRjE1DVp9f":"c:\\dentalempireos\\tmp\\import-14-trust-assets\\images\\img_07.webp"}